cbcbeat/__init__.py
cbcbeat/bidomainsolver.py
cbcbeat/cardiacmodels.py
cbcbeat/cellsolver.py
cbcbeat/dolfinimport.py
cbcbeat/gossplittingsolver.py
cbcbeat/gotran2cellmodel.py
cbcbeat/markerwisefield.py
cbcbeat/monodomainsolver.py
cbcbeat/splittingsolver.py
cbcbeat/utils.py
cbcbeat/cellmodels/__init__.py
cbcbeat/cellmodels/beeler_reuter_1977.py
cbcbeat/cellmodels/cardiaccellmodel.py
cbcbeat/cellmodels/fenton_karma_1998_BR_altered.py
cbcbeat/cellmodels/fenton_karma_1998_MLR1_altered.py
cbcbeat/cellmodels/fitzhughnagumo.py
cbcbeat/cellmodels/fitzhughnagumo_manual.py
cbcbeat/cellmodels/grandi_pasqualini_bers_2010.py
cbcbeat/cellmodels/nocellmodel.py
cbcbeat/cellmodels/rogers_mcculloch_manual.py
cbcbeat/cellmodels/tentusscher_2004_mcell.py
cbcbeat/cellmodels/tentusscher_2004_mcell_cont.py
cbcbeat/cellmodels/tentusscher_2004_mcell_disc.py
cbcbeat/cellmodels/tentusscher_panfilov_2006_M_cell.py
cbcbeat/cellmodels/tentusscher_panfilov_2006_epi_cell.py
cbcbeat-2023.2.0.dist-info/COPYING
cbcbeat-2023.2.0.dist-info/METADATA
cbcbeat-2023.2.0.dist-info/WHEEL
cbcbeat-2023.2.0.dist-info/entry_points.txt
cbcbeat-2023.2.0.dist-info/top_level.txt
cbcbeat-2023.2.0.dist-info/RECORD
