Metadata-Version: 2.1
Name: cbcbeat
Version: 2023.2.0
Summary: An adjoint-enabled framework for computational cardiac electrophysiology
Author: J.E hake, P.E Farrel, S. W. Funke
Author-email: "M. E. Rognes" <meg@simula.no>
License-File: COPYING
Requires-Dist: numpy
Provides-Extra: all
Requires-Dist: cbcbeat[test] ; extra == 'all'
Requires-Dist: cbcbeat[docs] ; extra == 'all'
Requires-Dist: cbcbeat[pypi] ; extra == 'all'
Requires-Dist: cbcbeat[dev] ; extra == 'all'
Provides-Extra: docs
Requires-Dist: sphinx ; extra == 'docs'
Requires-Dist: sphinx-book-theme ; extra == 'docs'
Provides-Extra: goss
Requires-Dist: pygoss ; extra == 'goss'
Provides-Extra: gotran
Requires-Dist: gotran ; extra == 'gotran'
Provides-Extra: pypi
Requires-Dist: twine ; extra == 'pypi'
Requires-Dist: build ; extra == 'pypi'
Provides-Extra: test
Requires-Dist: pytest ; extra == 'test'
Requires-Dist: pytest-cov ; extra == 'test'
Requires-Dist: matplotlib ; extra == 'test'
